{
 "url": "https://www.3m.com/3M/en_US/p/d/b5005329122/",
 "canonical": "https://www.3m.com/3M/en_US/p/d/b5005329122/",
 "name": "3M™ Screen Printable Polyester Performance Durable Label Material 7029",
 "product_number": "",
 "stock_number": "B5005329122",
 "short_description": "3M™ Screen Printable Polyester Performance Durable Label Material 7029 is a durable, high performance material that offers good thermal stability and moisture resistance. This topcoated polyester label stock utilizes 3M™ Adhesive P1400 which is a high performance tackified acrylic designed for use in demanding environments, including outdoor applications.",
 "division": "Safety & Industrial Bus Group",
 "discontinued": false,
 "benefits": [
  "Facestocks (polyester and vinyl) and adhesives offer heat tolerance, clarity, and UV resistance",
  "Adhesive offers good UV resistance and excellent adhesion to a wide variety of substrates, including polyolefins.",
  "Liner provides easy sheet processing and is designed for the ultimate in layflat. The backside of this liner is not printable.",
  "Overlaminate delivers moisture and tear resistance"
 ],
 "attributes": {
  "Adhesive Thickness (Imperial)": [
   "0.9 mil"
  ],
  "Adhesive Thickness (Metric)": [
   "0.02 mm"
  ],
  "Adhesive Type": [
   "Emulsion Acrylic"
  ],
  "Backing Material": [
   "Polyester"
  ],
  "Backing Thickness (Imperial)": [
   "2 mil"
  ],
  "Brands": [
   "3M™"
  ],
  "Face Side Adhesive Thickness (Imperial)": [
   "0.9 mil"
  ],
  "Face Side Adhesive Thickness (Metric)": [
   "0.023 mm"
  ],
  "Face Side Adhesive Type": [
   "P1400 Permanent Tackified Acrylic"
  ],
  "Facestock Color": [
   "Clear"
  ],
  "Facestock Material": [
   "Polyester"
  ],
  "Facestock Thickness": [
   "2 mil"
  ],
  "Facestock Thickness (Metric)": [
   "0.05 mm"
  ],
  "Industries": [
   "Automotive",
   "Consumer Goods",
   "Converter Solutions",
   "Electronics",
   "General Industrial",
   "Medical",
   "Military & Government",
   "Packaging",
   "Specialty Vehicles",
   "Transportation"
  ],
  "Label Form": [
   "Sheet"
  ],
  "Maximum Operating Temperature (Celsius)": [
   "125 ℃"
  ],
  "Maximum Operating Temperature (Fahrenheit)": [
   "257 ℉"
  ],
  "Minimum Operating Temperature (Celsius)": [
   "-28.89 ℃"
  ],
  "Minimum Operating Temperature (Fahrenheit)": [
   "-20 ℉"
  ],
  "Nominal Adhesive Thickness (Imperial)": [
   "0.9 mil"
  ],
  "Overall Length (Imperial)": [
   "27 in"
  ],
  "Overall Length (Metric)": [
   "0.68 m"
  ],
  "Overall Width (Imperial)": [
   "20 in",
   "54 in"
  ],
  "Overall Width (Metric)": [
   "508 mm",
   "1371.6 mm"
  ],
  "Primary Liner": [
   "90# Polycoated Kraft"
  ],
  "Primary Liner Color": [
   "Brown"
  ],
  "Primary Liner Thickness (Imperial)": [
   "6.8 mil"
  ],
  "Primary Liner Thickness (Metric)": [
   "0.17 mm"
  ],
  "Printing Method": [
   "Flexo",
   "Screen",
   "Thermal Transfer",
   "UV Screen"
  ],
  "Product Color": [
   "Transparent"
  ],
  "Product Type": [
   "Label"
  ],
  "Removability": [
   "Not Removable"
  ],
  "Smallest Saleable Unit": [
   "Roll",
   "Sheet"
  ],
  "Surface Finish": [
   "Glossy"
  ],
  "Tape Thickness (Imperial)": [
   "2.9 mil"
  ],
  "Topcoat": [
   "TC"
  ],
  "Units per Case": [
   "100.0"
  ]
 },
 "tds_pdfs": [
  "https://multimedia.3m.com/mws/media/2396554O/3m-screen-printable-polyester-performance-durable-label-material-7029.pdf?&fn=3M-Screen-Printable-Polyester-Performance-Durable-Label-Material-7029.pdf"
 ],
 "resources": [
  {
   "title": "3M™ Sheet and Screen Label Material 7029",
   "url": "https://cdmsweb.3m.com/ingredientcommunication/file/Media/FT5Y0mC628I",
   "contentType": "Regulatory Data Sheet"
  }
 ],
 "breadcrumb": [
  "",
  "",
  "",
  "",
  ""
 ],
 "discovery": {
  "material_number": "7029",
  "title": "3M™ Screen Printable Polyester Performance Durable Label Material 7029",
  "industries": [
   "Manufacturing",
   "Automotive",
   "Electronics",
   "Transportation"
  ]
 }
}